proxy_bonanza/__init__.py
proxy_bonanza/client.py
proxy_bonanza-1.0.2.dist-info/DESCRIPTION.rst
proxy_bonanza-1.0.2.dist-info/METADATA
proxy_bonanza-1.0.2.dist-info/metadata.json
proxy_bonanza-1.0.2.dist-info/RECORD
proxy_bonanza-1.0.2.dist-info/top_level.txt
proxy_bonanza-1.0.2.dist-info/WHEEL
